python_vscode_template/__init__.py
python_vscode_template/arithmetic.py
python_vscode_template/my_script.py
python_vscode_template/pokemon.py
python_vscode_template-0.0.1.dist-info/entry_points.txt
python_vscode_template-0.0.1.dist-info/LICENSE
python_vscode_template-0.0.1.dist-info/WHEEL
python_vscode_template-0.0.1.dist-info/METADATA
python_vscode_template-0.0.1.dist-info/RECORD
