Metadata-Version: 2.1
Name: python_vscode_template
Version: 0.0.1
Summary: python_vscode_template example
Author-email: David Groves <github@fibrecat.org>
Requires-Python: >=3.10
Project-URL: Home, https://github.com/davidgroves/Python-VSCode-Template
